{"name":"黑色旗帜","infos":{"用途":["重命名","图案","复制","地图标记","灾厄旗帜","燃料","合成材料"],"简介":["旗帜是一种装饰性方块，可以通过织布机自由创作旗帜内容。"],"ID":["gray_banner","cyan_banner","red_banner","blue_wall_banner","green_wall_banner","standing_banner","light_blue_banner","red_wall_banner","gray_wall_banner","lime_banner","light_blue_wall_banner","lime_wall_banner","brown_wall_banner","black_wall_banner","yellow_banner","white_wall_banner","magenta_banner","brown_banner","Banner","white_banner","purple_banner","green_banner","banner","blue_banner","orange_banner","light_gray_banner","magenta_wall_banner","yellow_wall_banner","light_gray_wall_banner","orange_wall_banner","cyan_wall_banner","purple_wall_banner","black_banner","wall_banner","pink_wall_banner","pink_banner"],"获取":["合成","灾厄旗帜","交易"],"生成":["自然生成"]}}